moller/__discovery.py
moller/__init__.py
moller/__main__.py
moller/ctrl.py
moller/filter_test.py
moller/gui.py
moller/moller_regs.json
moller/signal_generator.py
moller/signal_generator_agilent_33250a.py
moller/signal_generator_srs_ds360.py
moller/util.py
moller-1.2.1.dist-info/LICENSE
moller-1.2.1.dist-info/METADATA
moller-1.2.1.dist-info/WHEEL
moller-1.2.1.dist-info/entry_points.txt
moller-1.2.1.dist-info/top_level.txt
moller-1.2.1.dist-info/RECORD
