Metadata-Version: 2.2
Name: moller
Version: 1.2.1
Summary: package for MOLLER Experiment
Author-email: Bryerton Shaw <bryerton@triumf.ca>
Maintainer-email: Bryerton Shaw <bryerton@triumf.ca>
License: MIT License
License-File: LICENSE
Requires-Dist: numpy
Requires-Dist: matplotlib
Requires-Dist: pyzmq
Provides-Extra: dev
Requires-Dist: tox; extra == "dev"
